ZettyColor/Box.py
ZettyColor/Logger.py
ZettyColor/Menu.py
ZettyColor/Table.py
ZettyColor/ZtColors.py
ZettyColor/__init__.py
zettycolor-0.2.1.dist-info/licenses/LICENSE
zettycolor-0.2.1.dist-info/METADATA
zettycolor-0.2.1.dist-info/WHEEL
zettycolor-0.2.1.dist-info/top_level.txt
zettycolor-0.2.1.dist-info/RECORD
