Metadata-Version: 2.4
Name: ZettyColor
Version: 0.2.1
Summary: Terminal style
Author: Zetty
License: MIT
Requires-Python: >=3.7
License-File: LICENSE
Dynamic: license-file
